AUTHORS
MANIFEST.in
README.rst
UNLICENSE
setup.py
tavutil/__init__.py
tavutil/async.py
tavutil/crypto.py
tavutil/daemon.py
tavutil/dict.py
tavutil/env.py
tavutil/exception.py
tavutil/io.py
tavutil/ip.py
tavutil/jsonp.py
tavutil/lzf.c
tavutil/optcomplete.py
tavutil/optimise.py
tavutil/paypalx.py
tavutil/redis.py
tavutil/sanitise.py
tavutil/scm.py
tavutil/test_paypalx.py
tavutil/validation.py
tavutil/zeroconf.py
tavutil.egg-info/PKG-INFO
tavutil.egg-info/SOURCES.txt
tavutil.egg-info/dependency_links.txt
tavutil.egg-info/requires.txt
tavutil.egg-info/top_level.txt
tavutil.egg-info/zip-safe
tavutil/lzf/Changes
tavutil/lzf/LICENSE.txt
tavutil/lzf/README
tavutil/lzf/lzf.h
tavutil/lzf/lzfP.h
tavutil/lzf/lzf_c.c
tavutil/lzf/lzf_d.c