Metadata-Version: 1.1
Name: tavutil
Version: 1.0.3
Summary: A collection of utility modules
Home-page: https://github.com/tav/tavutil
Author: tav
Author-email: tav@espians.com
License: Public Domain
Keywords: async,crypto,sandbox,utility,redis,zeroconf
Platform: UNKNOWN
Classifier: Development Status :: 5 - Production/Stable
Classifier: Intended Audience :: Developers
Classifier: License :: Public Domain
Classifier: Operating System :: OS Independent
Classifier: Programming Language :: C
Classifier: Programming Language :: Cython
Classifier: Programming Language :: Python
